linkandtrack/__init__.py
linkandtrack/client_exceptions/__init__.py
linkandtrack/client_exceptions/client_error.py
linkandtrack/linkandtrack.py
pylinkandtrack-0.1.1.dist-info/LICENSE
pylinkandtrack-0.1.1.dist-info/METADATA
pylinkandtrack-0.1.1.dist-info/WHEEL
pylinkandtrack-0.1.1.dist-info/RECORD
