Metadata-Version: 2.1
Name: pylinkandtrack
Version: 0.1.1
Summary: Uma interface amigável para a API de rastreamento de encomendas dos Correios desenvolvida pela Link & Track.
License: MIT
Author: diaszano
Author-email: luucas.dsantos@gmail.com
Requires-Python: >=3.11,<4.0
Classifier: Development Status :: 4 - Beta
Classifier: License :: OSI Approved :: MIT License
Classifier: Natural Language :: Portuguese (Brazilian)
Classifier: Programming Language :: Python :: 3
Classifier: Programming Language :: Python :: 3.11
Classifier: Topic :: Adaptive Technologies
Classifier: Topic :: Software Development :: Libraries :: Python Modules
Classifier: Topic :: Utilities
Classifier: Typing :: Typed
Requires-Dist: aiohttp (>=3.8.5,<4.0.0)
Project-URL: Bug Tracker, https://github.com/Diaszano/pylinkandtrack/issues
Project-URL: Código, https://github.com/Diaszano/pylinkandtrack
Project-URL: Documentação, https://pylinkandtrack.readthedocs.io/en/latest/
